ktext/__init__.py
ktext/data_gen.py
ktext/preprocess.py
ktext-0.40.dist-info/LICENSE
ktext-0.40.dist-info/METADATA
ktext-0.40.dist-info/WHEEL
ktext-0.40.dist-info/top_level.txt
ktext-0.40.dist-info/RECORD
